{
  "$schema": "https://typedoc.org/schema.json",
  "entryPoints": ["../src"],
  "exclude": [],
  "name": "My Extension Kit Doc 🌀",
  "navigationLinks": {
    "⚡ Back to Github": "https://github.com/tmslpm/my-extension-kit"
  },
  "entryPointStrategy": "expand",
  "visibilityFilters": {
    "protected": true,
    "private": true,
    "inherited": true,
    "external": true,
    "@alpha": true,
    "@beta": true
  },
  "excludePrivate": true,
  "includeVersion": true,
  "customCss": "typedoc.css",
  "groupOrder": [
    "References",
    "Modules",
    "Namespaces",
    "Enumerations",
    "Enumeration Members",
    "Classes",
    "Interfaces",
    "Type Aliases",
    "Constructors",
    "Properties",
    "Variables",
    "Functions",
    "Methods",
    "Accessors"
  ]
}
